filetrack/Trackfile.py
filetrack/__init__.py
filetrack/__main__.py
filetrack/command_line.py
filetrack-0.1.2.dist-info/licenses/LICENSE
filetrack-0.1.2.dist-info/METADATA
filetrack-0.1.2.dist-info/WHEEL
filetrack-0.1.2.dist-info/entry_points.txt
filetrack-0.1.2.dist-info/top_level.txt
filetrack-0.1.2.dist-info/RECORD
