Metadata-Version: 2.4
Name: filetrack
Version: 0.1.2
Summary: Tracking file changes according to the record file.
Author-email: Kyan <kai@kyan001.com>
License: BSD 3-Clause License
Project-URL: Homepage, https://github.com/kyan001/PyFileTrack
Project-URL: Changelog, https://github.com/kyan001/PyFileTrack/blob/master/CHANGELOG.md
Project-URL: Issue Tracker, https://github.com/kyan001/PyFileTrack/issues
Project-URL: Source Code, https://github.com/kyan001/PyFileTrack
Keywords: python3,file,track,cli
Classifier: Intended Audience :: Developers
Classifier: Intended Audience :: End Users/Desktop
Classifier: License :: OSI Approved :: BSD License
Classifier: Programming Language :: Python :: 3
Classifier: Programming Language :: Python :: 3 :: Only
Requires-Python: >=3.10
License-File: LICENSE
Requires-Dist: consoleiotools
Requires-Dist: consolecmdtools
Requires-Dist: fuzzyfinder
Requires-Dist: xxhash
Provides-Extra: dev
Requires-Dist: build; extra == "dev"
Requires-Dist: twine; extra == "dev"
Provides-Extra: opt
Requires-Dist: tomlkit; extra == "opt"
Dynamic: license-file
